molecule_inspec/__init__.py
molecule_inspec/inspec.py
molecule_inspec/cookiecutter/scenario/verifier/inspec/cookiecutter.json
molecule_inspec/cookiecutter/scenario/verifier/inspec/{{cookiecutter.molecule_directory}}/{{cookiecutter.scenario_name}}/verify.yml
molecule_inspec/cookiecutter/scenario/verifier/inspec/{{cookiecutter.molecule_directory}}/{{cookiecutter.scenario_name}}/{{cookiecutter.verifier_directory}}/test_default.rb
molecule_inspec/test/__init__.py
molecule_inspec/test/conftest.py
molecule_inspec/test/test_command.py
molecule_inspec/test/scenarios/docker/centos7/molecule/default/converge.yml
molecule_inspec/test/scenarios/docker/centos7/molecule/default/molecule.yml
molecule_inspec/test/scenarios/docker/centos7/molecule/default/verify.yml
molecule_inspec/test/scenarios/docker/centos7/molecule/default/tests/inspec.yml
molecule_inspec/test/scenarios/docker/centos7/molecule/default/tests/controls/install.rb
molecule_inspec/test/scenarios/docker/centos7/molecule/default/tests/controls/test_files.rb
molecule_inspec/test/scenarios/docker/ubuntu18.04/molecule/default/converge.yml
molecule_inspec/test/scenarios/docker/ubuntu18.04/molecule/default/molecule.yml
molecule_inspec/test/scenarios/docker/ubuntu18.04/molecule/default/verify.yml
molecule_inspec/test/scenarios/docker/ubuntu18.04/molecule/default/tests/inspec.yml
molecule_inspec/test/scenarios/docker/ubuntu18.04/molecule/default/tests/controls/install.rb
molecule_inspec/test/scenarios/docker/ubuntu18.04/molecule/default/tests/controls/test_files.rb
molecule_inspec-1.1.dist-info/LICENSE
molecule_inspec-1.1.dist-info/METADATA
molecule_inspec-1.1.dist-info/WHEEL
molecule_inspec-1.1.dist-info/entry_points.txt
molecule_inspec-1.1.dist-info/top_level.txt
molecule_inspec-1.1.dist-info/RECORD
