Metadata-Version: 2.1
Name: molecule-inspec
Version: 1.1
Summary: Inspec Molecule Plugin :: run molecule tests with inspec as verifier
Home-page: https://github.com/pycontribs/molecule-inspec
Author: Ansible by Red Hat
Author-email: info@ansible.com
Maintainer: Ansible by Red Hat
Maintainer-email: info@ansible.com
License: MIT
Project-URL: Bug Tracker, https://github.com/ansible-community/molecule-inspec/issues
Project-URL: Release Management, https://github.com/ansible-community/molecule-inspec/releases
Project-URL: CI, https://github.com/ansible-community/molecule-inspec/actions
Project-URL: Code of Conduct, https://docs.ansible.com/ansible/latest/community/code_of_conduct.html
Project-URL: Documentation, https://molecule.readthedocs.io
Project-URL: Discussions, https://github.com/ansible-community/molecule/discussions
Project-URL: Source Code, https://github.com/ansible-community/molecule-inspec
Keywords: ansible,roles,testing,molecule,plugin,inspec,verifier
Platform: UNKNOWN
Classifier: Development Status :: 5 - Production/Stable
Classifier: Environment :: Console
Classifier: Intended Audience :: Developers
Classifier: Intended Audience :: Information Technology
Classifier: Intended Audience :: System Administrators
Classifier: License :: OSI Approved :: MIT License
Classifier: Natural Language :: English
Classifier: Operating System :: OS Independent
Classifier: Programming Language :: Python :: 3
Classifier: Programming Language :: Python :: 3.6
Classifier: Programming Language :: Python :: 3.7
Classifier: Programming Language :: Python :: 3.8
Classifier: Topic :: System :: Systems Administration
Classifier: Topic :: Utilities
Requires-Python: >=3.6
Requires-Dist: ansible (>=2.10.3)
Requires-Dist: molecule (>=3.2.0)
Requires-Dist: pyyaml (<6,>=5.1)
Provides-Extra: docs
Requires-Dist: simplejson ; extra == 'docs'
Requires-Dist: Sphinx ; extra == 'docs'
Requires-Dist: sphinx-ansible-theme (>=0.2.2) ; extra == 'docs'
Provides-Extra: lint
Requires-Dist: pre-commit (>=1.21.0) ; extra == 'lint'
Provides-Extra: test
Requires-Dist: molecule[test] ; extra == 'test'
Requires-Dist: pytest-helpers-namespace ; extra == 'test'
